psc/__init__.py
psc/__main__.py
python_script_converter-1.2.dist-info/LICENSE
python_script_converter-1.2.dist-info/METADATA
python_script_converter-1.2.dist-info/WHEEL
python_script_converter-1.2.dist-info/entry_points.txt
python_script_converter-1.2.dist-info/top_level.txt
python_script_converter-1.2.dist-info/RECORD
