Metadata-Version: 2.1
Name: python-script-converter
Version: 1.2
Summary: This is a tiny tool used to convert a python script to a executable file(only for Mac and Linux).
Home-page: https://github.com/ZYunH/Python-script-converter
Author: ZhangYunHao
Author-email: zyunhjob@163.com
License: MIT Licence
Keywords: python tool converter
Platform: Mac Linux
